pycrtsh/__init__.py
pycrtsh/api.py
pycrtsh/cli.py
pycrtsh-0.3.13.dist-info/LICENSE
pycrtsh-0.3.13.dist-info/METADATA
pycrtsh-0.3.13.dist-info/WHEEL
pycrtsh-0.3.13.dist-info/entry_points.txt
pycrtsh-0.3.13.dist-info/top_level.txt
pycrtsh-0.3.13.dist-info/RECORD
