Metadata-Version: 2.1
Name: pycrtsh
Version: 0.3.13
Summary: Python library to request crt.sh certificate information
Home-page: https://github.com/Te-k/pycrtsh
Author: Tek
Author-email: tek@randhome.io
License: MIT
Keywords: security
Classifier: Programming Language :: Python :: 3
Classifier: License :: OSI Approved :: MIT License
Classifier: Operating System :: OS Independent
License-File: LICENSE
Requires-Dist: requests
Requires-Dist: lxml==5.3.0
Requires-Dist: beautifulsoup4>=4.12.3
Requires-Dist: python-dateutil
Requires-Dist: psycopg2-binary>=2.9.10
